{
  "scrapedAt": "2025-10-03T05:13:37.400Z",
  "leagueId": "drbLSZtcWd7r",
  "balance": 765600,
  "team": [
    {
      "name": "Remiro",
      "position": "PT",
      "team": "Real Sociedad",
      "price": 4310000,
      "url": "/la-liga/players/alex-remiro",
      "clause": null,
      "clauseDeposited": null,
      "owner": null,
      "ownerUrl": null,
      "clauseUnlockIn": "Disponible",
      "source": "equipo"
    },
    {
      "name": "Le Normand",
      "position": "DEF",
      "team": "Atlético",
      "price": 3260000,
      "url": "/la-liga/players/le-normand",
      "clause": null,
      "clauseDeposited": null,
      "owner": null,
      "ownerUrl": null,
      "clauseUnlockIn": "Disponible",
      "source": "equipo"
    },
    {
      "name": "Chust",
      "position": "DEF",
      "team": "Elche",
      "price": 1190000,
      "url": "/la-liga/players/chust",
      "clause": null,
      "clauseDeposited": null,
      "owner": null,
      "ownerUrl": null,
      "clauseUnlockIn": "Disponible",
      "source": "equipo"
    },
    {
      "name": "Javi Rodríguez",
      "position": "DEF",
      "team": "Celta",
      "price": 1270000,
      "url": "/la-liga/players/javier-rodriguez",
      "clause": null,
      "clauseDeposited": null,
      "owner": null,
      "ownerUrl": null,
      "clauseUnlockIn": "Disponible",
      "source": "equipo"
    },
    {
      "name": "Valverde",
      "position": "MED",
      "team": "Real Madrid",
      "price": 11380000,
      "url": "/la-liga/players/fede-valverde",
      "clause": 23460000,
      "clauseDeposited": null,
      "owner": null,
      "ownerUrl": "/user/los-cholitoos-12726359",
      "clauseUnlockIn": "Disponible",
      "source": "equipo"
    },
    {
      "name": "Gallagher",
      "position": "MED",
      "team": "Atlético",
      "price": 1640000,
      "url": "/la-liga/players/conor-gallagher",
      "clause": null,
      "clauseDeposited": null,
      "owner": null,
      "ownerUrl": null,
      "clauseUnlockIn": "Disponible",
      "source": "equipo"
    },
    {
      "name": "Óscar Valentín",
      "position": "MED",
      "team": "Rayo Vallecano",
      "price": 1240000,
      "url": "/la-liga/players/o-valentin",
      "clause": null,
      "clauseDeposited": null,
      "owner": null,
      "ownerUrl": null,
      "clauseUnlockIn": "Disponible",
      "source": "equipo"
    },
    {
      "name": "Mascarell",
      "position": "MED",
      "team": "Mallorca",
      "price": 310000,
      "url": "/la-liga/players/omar-mascarell",
      "clause": 1395000,
      "clauseDeposited": null,
      "owner": null,
      "ownerUrl": "/user/los-cholitoos-12726359",
      "clauseUnlockIn": "Disponible",
      "source": "equipo"
    },
    {
      "name": "Dani Rodríguez",
      "position": "MED",
      "team": "Mallorca",
      "price": 1310000,
      "url": "/la-liga/players/dani-rodriguez",
      "clause": null,
      "clauseDeposited": null,
      "owner": null,
      "ownerUrl": null,
      "clauseUnlockIn": "Disponible",
      "source": "equipo"
    },
    {
      "name": "Asano",
      "position": "DEL",
      "team": "Mallorca",
      "price": 670000,
      "url": "/la-liga/players/takuma-asano",
      "clause": 1560000,
      "clauseDeposited": null,
      "owner": null,
      "ownerUrl": "/user/los-cholitoos-12726359",
      "clauseUnlockIn": "Disponible",
      "source": "equipo"
    },
    {
      "name": "Domenech",
      "position": "DEL",
      "team": "Mallorca",
      "price": 260000,
      "url": "/la-liga/players/marc-domenech",
      "clause": 390000,
      "clauseDeposited": null,
      "owner": null,
      "ownerUrl": "/user/los-cholitoos-12726359",
      "clauseUnlockIn": "Disponible",
      "source": "equipo"
    },
    {
      "name": "Forés",
      "position": "DEL",
      "team": "Real Oviedo",
      "price": 220000,
      "url": "/la-liga/players/alex-fores",
      "clause": 330000,
      "clauseDeposited": null,
      "owner": null,
      "ownerUrl": "/user/los-cholitoos-12726359",
      "clauseUnlockIn": "Disponible",
      "source": "equipo"
    }
  ],
  "market": [
    {
      "name": "Griezmann",
      "position": "DEL",
      "team": "Atlético",
      "price": 9320000,
      "listedPrice": 4660000,
      "timeRemaining": "en 2 días",
      "deadline": "5/10/25, 5:09",
      "url": "/la-liga/players/griezmann",
      "clause": null,
      "clauseDeposited": null,
      "owner": null,
      "ownerUrl": null,
      "clauseUnlockIn": "Disponible",
      "source": "mercado"
    },
    {
      "name": "Ceballos",
      "position": "MED",
      "team": "Real Madrid",
      "price": 3360000,
      "listedPrice": 1680000,
      "timeRemaining": "en 2 días",
      "deadline": "5/10/25, 5:09",
      "url": "/la-liga/players/dani-ceballos",
      "clause": null,
      "clauseDeposited": null,
      "owner": null,
      "ownerUrl": null,
      "clauseUnlockIn": "Disponible",
      "source": "mercado"
    },
    {
      "name": "Lunin",
      "position": "PT",
      "team": "Real Madrid",
      "price": 580000,
      "listedPrice": 290000,
      "timeRemaining": "en 2 días",
      "deadline": "5/10/25, 5:09",
      "url": "/la-liga/players/andriy-lunin",
      "clause": 450000,
      "clauseDeposited": null,
      "owner": null,
      "ownerUrl": "/user/palas-c-d-8074955",
      "clauseUnlockIn": "Disponible",
      "source": "mercado"
    },
    {
      "name": "Torró",
      "position": "MED",
      "team": "Osasuna",
      "price": 6000000,
      "listedPrice": 3000000,
      "timeRemaining": "en 2 días",
      "deadline": "5/10/25, 5:09",
      "url": "/la-liga/players/lucas-torro",
      "clause": 5183250,
      "clauseDeposited": null,
      "owner": null,
      "ownerUrl": "/user/palas-c-d-8074955",
      "clauseUnlockIn": "Disponible",
      "source": "mercado"
    },
    {
      "name": "Natan",
      "position": "DEF",
      "team": "Betis",
      "price": 4680000,
      "listedPrice": 2340000,
      "timeRemaining": "en 2 días",
      "deadline": "5/10/25, 5:09",
      "url": "/la-liga/players/natan",
      "clause": null,
      "clauseDeposited": null,
      "owner": null,
      "ownerUrl": null,
      "clauseUnlockIn": "Disponible",
      "source": "mercado"
    },
    {
      "name": "Jesús Vázquez",
      "position": "DEF",
      "team": "Valencia",
      "price": 900000,
      "listedPrice": 450000,
      "timeRemaining": "en 2 días",
      "deadline": "5/10/25, 5:09",
      "url": "/la-liga/players/jesus-vazquez",
      "clause": 675000,
      "clauseDeposited": null,
      "owner": null,
      "ownerUrl": "/user/palas-c-d-8074955",
      "clauseUnlockIn": "Disponible",
      "source": "mercado"
    },
    {
      "name": "Moleiro",
      "position": "MED",
      "team": "Villarreal",
      "price": 7040000,
      "listedPrice": 3520000,
      "timeRemaining": "en 2 días",
      "deadline": "5/10/25, 5:09",
      "url": "/la-liga/players/alberto-moleiro",
      "clause": null,
      "clauseDeposited": null,
      "owner": null,
      "ownerUrl": null,
      "clauseUnlockIn": "Disponible",
      "source": "mercado"
    },
    {
      "name": "Carlos Vicente",
      "position": "DEL",
      "team": "Alavés",
      "price": 8300000,
      "listedPrice": 4150000,
      "timeRemaining": "en 2 días",
      "deadline": "5/10/25, 5:09",
      "url": "/la-liga/players/carlos-vicente",
      "clause": null,
      "clauseDeposited": null,
      "owner": null,
      "ownerUrl": null,
      "clauseUnlockIn": "Disponible",
      "source": "mercado"
    },
    {
      "name": "Mateu Morey",
      "position": "DEF",
      "team": "Mallorca",
      "price": 2580000,
      "listedPrice": 1290000,
      "timeRemaining": "en 2 días",
      "deadline": "5/10/25, 5:09",
      "url": "/la-liga/players/mateu-morey",
      "clause": null,
      "clauseDeposited": null,
      "owner": null,
      "ownerUrl": null,
      "clauseUnlockIn": "Disponible",
      "source": "mercado"
    },
    {
      "name": "Buchanan",
      "position": "MED",
      "team": "Villarreal",
      "price": 12840000,
      "listedPrice": 6420000,
      "timeRemaining": "en 2 días",
      "deadline": "5/10/25, 5:09",
      "url": "/la-liga/players/tajon-buchanan",
      "clause": 9630000,
      "clauseDeposited": null,
      "owner": null,
      "ownerUrl": "/user/palas-c-d-8074955",
      "clauseUnlockIn": "Disponible",
      "source": "mercado"
    },
    {
      "name": "Roberto Fernández",
      "position": "DEL",
      "team": "Espanyol",
      "price": 7080000,
      "listedPrice": 3540000,
      "timeRemaining": "en 2 días",
      "deadline": "5/10/25, 5:09",
      "url": "/la-liga/players/r-fernandez",
      "clause": null,
      "clauseDeposited": null,
      "owner": null,
      "ownerUrl": null,
      "clauseUnlockIn": "Disponible",
      "source": "mercado"
    },
    {
      "name": "Salinas",
      "position": "DEF",
      "team": "Espanyol",
      "price": 460000,
      "listedPrice": 230000,
      "timeRemaining": "en 2 días",
      "deadline": "5/10/25, 5:09",
      "url": "/la-liga/players/jose-salinas",
      "clause": null,
      "clauseDeposited": null,
      "owner": null,
      "ownerUrl": null,
      "clauseUnlockIn": "Disponible",
      "source": "mercado"
    },
    {
      "name": "Dolan",
      "position": "DEL",
      "team": "Espanyol",
      "price": 5160000,
      "listedPrice": 2580000,
      "timeRemaining": "en 2 días",
      "deadline": "5/10/25, 5:09",
      "url": "/la-liga/players/dolan",
      "clause": null,
      "clauseDeposited": null,
      "owner": null,
      "ownerUrl": null,
      "clauseUnlockIn": "Disponible",
      "source": "mercado"
    },
    {
      "name": "Barrenetxea",
      "position": "MED",
      "team": "Real Sociedad",
      "price": 4720000,
      "listedPrice": 4720000,
      "timeRemaining": "mañana",
      "deadline": "4/10/25, 5:00",
      "url": "/la-liga/players/barrenetxea",
      "clause": null,
      "clauseDeposited": null,
      "owner": null,
      "ownerUrl": null,
      "clauseUnlockIn": "Disponible",
      "source": "mercado"
    },
    {
      "name": "Pedrosa",
      "position": "DEF",
      "team": "Elche",
      "price": 930000,
      "listedPrice": 930000,
      "timeRemaining": "mañana",
      "deadline": "4/10/25, 5:00",
      "url": "/la-liga/players/pedrosa",
      "clause": null,
      "clauseDeposited": null,
      "owner": null,
      "ownerUrl": null,
      "clauseUnlockIn": "Disponible",
      "source": "mercado"
    },
    {
      "name": "Budimir",
      "position": "DEL",
      "team": "Osasuna",
      "price": 8580000,
      "listedPrice": 8580000,
      "timeRemaining": "mañana",
      "deadline": "4/10/25, 5:00",
      "url": "/la-liga/players/ante-budimir",
      "clause": null,
      "clauseDeposited": null,
      "owner": null,
      "ownerUrl": null,
      "clauseUnlockIn": "Disponible",
      "source": "mercado"
    },
    {
      "name": "Mumin",
      "position": "DEF",
      "team": "Rayo Vallecano",
      "price": 370000,
      "listedPrice": 370000,
      "timeRemaining": "mañana",
      "deadline": "4/10/25, 5:00",
      "url": "/la-liga/players/abdul-mumin",
      "clause": null,
      "clauseDeposited": null,
      "owner": null,
      "ownerUrl": null,
      "clauseUnlockIn": "Disponible",
      "source": "mercado"
    },
    {
      "name": "Sow",
      "position": "MED",
      "team": "Sevilla",
      "price": 1220000,
      "listedPrice": 1220000,
      "timeRemaining": "mañana",
      "deadline": "4/10/25, 5:00",
      "url": "/la-liga/players/djibril-sow",
      "clause": null,
      "clauseDeposited": null,
      "owner": null,
      "ownerUrl": null,
      "clauseUnlockIn": "Disponible",
      "source": "mercado"
    },
    {
      "name": "Abel Ruiz",
      "position": "DEL",
      "team": "Girona",
      "price": 220000,
      "listedPrice": 220000,
      "timeRemaining": "mañana",
      "deadline": "4/10/25, 5:00",
      "url": "/la-liga/players/abel-ruiz",
      "clause": null,
      "clauseDeposited": null,
      "owner": null,
      "ownerUrl": null,
      "clauseUnlockIn": "Disponible",
      "source": "mercado"
    },
    {
      "name": "Adrián Liso",
      "position": "DEL",
      "team": "Getafe",
      "price": 2920000,
      "listedPrice": 2920000,
      "timeRemaining": "mañana",
      "deadline": "4/10/25, 5:00",
      "url": "/la-liga/players/adrian-liso",
      "clause": null,
      "clauseDeposited": null,
      "owner": null,
      "ownerUrl": null,
      "clauseUnlockIn": "Disponible",
      "source": "mercado"
    },
    {
      "name": "Davinchi",
      "position": "DEF",
      "team": "Getafe",
      "price": 1220000,
      "listedPrice": 1220000,
      "timeRemaining": "mañana",
      "deadline": "4/10/25, 5:00",
      "url": "/la-liga/players/davinchi",
      "clause": null,
      "clauseDeposited": null,
      "owner": null,
      "ownerUrl": null,
      "clauseUnlockIn": "Disponible",
      "source": "mercado"
    },
    {
      "name": "Luka Ilic",
      "position": "MED",
      "team": "Real Oviedo",
      "price": 1290000,
      "listedPrice": 1290000,
      "timeRemaining": "mañana",
      "deadline": "4/10/25, 5:00",
      "url": "/la-liga/players/luka-ilic",
      "clause": null,
      "clauseDeposited": null,
      "owner": null,
      "ownerUrl": null,
      "clauseUnlockIn": "Disponible",
      "source": "mercado"
    },
    {
      "name": "Koke",
      "position": "MED",
      "team": "Atlético",
      "price": 5460000,
      "listedPrice": 2930000,
      "timeRemaining": "en 2 días",
      "deadline": "5/10/25, 5:00",
      "url": "/la-liga/players/koke",
      "clause": 6395000,
      "clauseDeposited": 1000000,
      "owner": null,
      "ownerUrl": "/user/forza-depor-3712719",
      "clauseUnlockIn": "Disponible",
      "source": "mercado"
    },
    {
      "name": "Isco",
      "position": "MED",
      "team": "Betis",
      "price": 12300000,
      "listedPrice": 6080000,
      "timeRemaining": "en 2 días",
      "deadline": "5/10/25, 5:00",
      "url": "/la-liga/players/isco",
      "clause": null,
      "clauseDeposited": null,
      "owner": null,
      "ownerUrl": null,
      "clauseUnlockIn": "Disponible",
      "source": "mercado"
    },
    {
      "name": "Ayoze",
      "position": "DEL",
      "team": "Villarreal",
      "price": 12840000,
      "listedPrice": 6320000,
      "timeRemaining": "en 2 días",
      "deadline": "5/10/25, 5:00",
      "url": "/la-liga/players/ayoze-perez",
      "clause": null,
      "clauseDeposited": null,
      "owner": null,
      "ownerUrl": null,
      "clauseUnlockIn": "Disponible",
      "source": "mercado"
    },
    {
      "name": "Borja Iglesias",
      "position": "DEL",
      "team": "Celta",
      "price": 10160000,
      "listedPrice": 5250000,
      "timeRemaining": "en 2 días",
      "deadline": "5/10/25, 5:00",
      "url": "/la-liga/players/borja-iglesias",
      "clause": null,
      "clauseDeposited": null,
      "owner": null,
      "ownerUrl": null,
      "clauseUnlockIn": "Disponible",
      "source": "mercado"
    },
    {
      "name": "Carlos Dominguez",
      "position": "DEF",
      "team": "Celta",
      "price": 640000,
      "listedPrice": 320000,
      "timeRemaining": "en 2 días",
      "deadline": "5/10/25, 5:00",
      "url": "/la-liga/players/carlos-dominguez",
      "clause": 480000,
      "clauseDeposited": null,
      "owner": null,
      "ownerUrl": "/user/forza-depor-3712719",
      "clauseUnlockIn": "Disponible",
      "source": "mercado"
    },
    {
      "name": "Zubeldia",
      "position": "DEF",
      "team": "Real Sociedad",
      "price": 3740000,
      "listedPrice": 1900000,
      "timeRemaining": "en 2 días",
      "deadline": "5/10/25, 5:00",
      "url": "/la-liga/players/zubeldia",
      "clause": null,
      "clauseDeposited": null,
      "owner": null,
      "ownerUrl": null,
      "clauseUnlockIn": "Disponible",
      "source": "mercado"
    },
    {
      "name": "Iván Martín",
      "position": "MED",
      "team": "Girona",
      "price": 4120000,
      "listedPrice": 2140000,
      "timeRemaining": "en 2 días",
      "deadline": "5/10/25, 5:00",
      "url": "/la-liga/players/ivan-martin",
      "clause": null,
      "clauseDeposited": null,
      "owner": null,
      "ownerUrl": null,
      "clauseUnlockIn": "Disponible",
      "source": "mercado"
    },
    {
      "name": "André Silva",
      "position": "DEL",
      "team": "Elche",
      "price": 7500000,
      "listedPrice": 3860000,
      "timeRemaining": "en 2 días",
      "deadline": "5/10/25, 5:00",
      "url": "/la-liga/players/andre-silva",
      "clause": null,
      "clauseDeposited": null,
      "owner": null,
      "ownerUrl": null,
      "clauseUnlockIn": "Disponible",
      "source": "mercado"
    },
    {
      "name": "Kike Barja",
      "position": "MED",
      "team": "Osasuna",
      "price": 300000,
      "listedPrice": 150000,
      "timeRemaining": "en 2 días",
      "deadline": "5/10/25, 5:00",
      "url": "/la-liga/players/kike-barja",
      "clause": null,
      "clauseDeposited": null,
      "owner": null,
      "ownerUrl": null,
      "clauseUnlockIn": "Disponible",
      "source": "mercado"
    },
    {
      "name": "Mbappé",
      "position": "DEL",
      "team": "Real Madrid",
      "price": 49240000,
      "listedPrice": 24680000,
      "timeRemaining": "en 2 días",
      "deadline": "5/10/25, 5:00",
      "url": "/la-liga/players/mbappe",
      "clause": 37020000,
      "clauseDeposited": null,
      "owner": null,
      "ownerUrl": "/user/forza-depor-3712719",
      "clauseUnlockIn": "Disponible",
      "source": "mercado"
    },
    {
      "name": "Ez Abde",
      "position": "DEL",
      "team": "Betis",
      "price": 9640000,
      "listedPrice": 5000000,
      "timeRemaining": "en 2 días",
      "deadline": "5/10/25, 5:00",
      "url": "/la-liga/players/abdessamad-ezzalzouli",
      "clause": 7723500,
      "clauseDeposited": null,
      "owner": null,
      "ownerUrl": "/user/forza-depor-3712719",
      "clauseUnlockIn": "Disponible",
      "source": "mercado"
    },
    {
      "name": "Ahijado",
      "position": "DEF",
      "team": "Real Oviedo",
      "price": 860000,
      "listedPrice": 490000,
      "timeRemaining": "en 2 días",
      "deadline": "5/10/25, 5:00",
      "url": "/la-liga/players/lucas-ahijado",
      "clause": null,
      "clauseDeposited": null,
      "owner": null,
      "ownerUrl": null,
      "clauseUnlockIn": "Disponible",
      "source": "mercado"
    },
    {
      "name": "Riedel",
      "position": "DEF",
      "team": "Espanyol",
      "price": 2780000,
      "listedPrice": 1480000,
      "timeRemaining": "en 2 días",
      "deadline": "5/10/25, 5:00",
      "url": "/la-liga/players/clemens-riedel",
      "clause": null,
      "clauseDeposited": null,
      "owner": null,
      "ownerUrl": null,
      "clauseUnlockIn": "Disponible",
      "source": "mercado"
    },
    {
      "name": "Iker Benito",
      "position": "MED",
      "team": "Osasuna",
      "price": 7600000,
      "listedPrice": 990000,
      "timeRemaining": "mañana",
      "deadline": "4/10/25, 22:51",
      "url": "/la-liga/players/iker-benito",
      "clause": 1800000,
      "clauseDeposited": null,
      "owner": null,
      "ownerUrl": "/user/emre-team-6720619",
      "clauseUnlockIn": "Disponible",
      "source": "mercado"
    },
    {
      "name": "Fornals",
      "position": "MED",
      "team": "Betis",
      "price": 13940000,
      "listedPrice": 7130000,
      "timeRemaining": "mañana",
      "deadline": "4/10/25, 22:10",
      "url": "/la-liga/players/fornals",
      "clause": 12695000,
      "clauseDeposited": 1000000,
      "owner": null,
      "ownerUrl": "/user/kenzoxs-3728853",
      "clauseUnlockIn": "Disponible",
      "source": "mercado"
    },
    {
      "name": "Moncayola",
      "position": "MED",
      "team": "Osasuna",
      "price": 7480000,
      "listedPrice": 3770000,
      "timeRemaining": "mañana",
      "deadline": "4/10/25, 22:10",
      "url": "/la-liga/players/moncayola",
      "clause": null,
      "clauseDeposited": null,
      "owner": null,
      "ownerUrl": null,
      "clauseUnlockIn": "Disponible",
      "source": "mercado"
    },
    {
      "name": "Calero",
      "position": "DEF",
      "team": "Espanyol",
      "price": 3940000,
      "listedPrice": 2020000,
      "timeRemaining": "mañana",
      "deadline": "4/10/25, 22:10",
      "url": "/la-liga/players/fernando-calero",
      "clause": 5030000,
      "clauseDeposited": 1000000,
      "owner": null,
      "ownerUrl": "/user/kenzoxs-3728853",
      "clauseUnlockIn": "Disponible",
      "source": "mercado"
    },
    {
      "name": "Pablo Ibáñez",
      "position": "MED",
      "team": "Alavés",
      "price": 3380000,
      "listedPrice": 1680000,
      "timeRemaining": "mañana",
      "deadline": "4/10/25, 22:10",
      "url": "/la-liga/players/pablo-ibanez",
      "clause": null,
      "clauseDeposited": null,
      "owner": null,
      "ownerUrl": null,
      "clauseUnlockIn": "Disponible",
      "source": "mercado"
    },
    {
      "name": "Galán",
      "position": "DEF",
      "team": "Atlético",
      "price": 780000,
      "listedPrice": 400000,
      "timeRemaining": "mañana",
      "deadline": "4/10/25, 22:10",
      "url": "/la-liga/players/javi-galan",
      "clause": null,
      "clauseDeposited": null,
      "owner": null,
      "ownerUrl": null,
      "clauseUnlockIn": "Disponible",
      "source": "mercado"
    },
    {
      "name": "Koundé",
      "position": "DEF",
      "team": "Barcelona",
      "price": 13820000,
      "listedPrice": 7020000,
      "timeRemaining": "mañana",
      "deadline": "4/10/25, 22:10",
      "url": "/la-liga/players/jules-kounde",
      "clause": null,
      "clauseDeposited": null,
      "owner": null,
      "ownerUrl": null,
      "clauseUnlockIn": "Disponible",
      "source": "mercado"
    },
    {
      "name": "Luis Milla",
      "position": "MED",
      "team": "Getafe",
      "price": 15760000,
      "listedPrice": 7890000,
      "timeRemaining": "mañana",
      "deadline": "4/10/25, 22:10",
      "url": "/la-liga/players/luis-milla",
      "clause": null,
      "clauseDeposited": null,
      "owner": null,
      "ownerUrl": null,
      "clauseUnlockIn": "Disponible",
      "source": "mercado"
    },
    {
      "name": "Baena",
      "position": "MED",
      "team": "Atlético",
      "price": 17180000,
      "listedPrice": 8640000,
      "timeRemaining": "mañana",
      "deadline": "4/10/25, 22:10",
      "url": "/la-liga/players/alex-baena",
      "clause": 14500500,
      "clauseDeposited": null,
      "owner": null,
      "ownerUrl": "/user/kenzoxs-3728853",
      "clauseUnlockIn": "Disponible",
      "source": "mercado"
    },
    {
      "name": "Tárrega",
      "position": "DEF",
      "team": "Valencia",
      "price": 6840000,
      "listedPrice": 3430000,
      "timeRemaining": "mañana",
      "deadline": "4/10/25, 22:10",
      "url": "/la-liga/players/cesar-tarrega",
      "clause": null,
      "clauseDeposited": null,
      "owner": null,
      "ownerUrl": null,
      "clauseUnlockIn": "Disponible",
      "source": "mercado"
    },
    {
      "name": "Batalla",
      "position": "PT",
      "team": "Rayo Vallecano",
      "price": 8620000,
      "listedPrice": 4280000,
      "timeRemaining": "mañana",
      "deadline": "4/10/25, 22:10",
      "url": "/la-liga/players/augusto-batalla",
      "clause": 6832500,
      "clauseDeposited": null,
      "owner": null,
      "ownerUrl": "/user/kenzoxs-3728853",
      "clauseUnlockIn": "Disponible",
      "source": "mercado"
    },
    {
      "name": "Etta Eyong",
      "position": "DEL",
      "team": "Levante",
      "price": 18320000,
      "listedPrice": 9340000,
      "timeRemaining": "mañana",
      "deadline": "4/10/25, 22:10",
      "url": "/la-liga/players/etta-eyong",
      "clause": 17410000,
      "clauseDeposited": 1700000,
      "owner": null,
      "ownerUrl": "/user/kenzoxs-3728853",
      "clauseUnlockIn": "Disponible",
      "source": "mercado"
    },
    {
      "name": "Ricardo Rodríguez",
      "position": "DEF",
      "team": "Betis",
      "price": 860000,
      "listedPrice": 480000,
      "timeRemaining": "mañana",
      "deadline": "4/10/25, 22:10",
      "url": "/la-liga/players/r-rodriguez",
      "clause": null,
      "clauseDeposited": null,
      "owner": null,
      "ownerUrl": null,
      "clauseUnlockIn": "Disponible",
      "source": "mercado"
    },
    {
      "name": "Alex Sancris",
      "position": "DEL",
      "team": "Getafe",
      "price": 700000,
      "listedPrice": 370000,
      "timeRemaining": "mañana",
      "deadline": "4/10/25, 22:10",
      "url": "/la-liga/players/alex-sancris",
      "clause": null,
      "clauseDeposited": null,
      "owner": null,
      "ownerUrl": null,
      "clauseUnlockIn": "Disponible",
      "source": "mercado"
    },
    {
      "name": "Gabriel Suazo",
      "position": "DEF",
      "team": "Sevilla",
      "price": 5780000,
      "listedPrice": 2940000,
      "timeRemaining": "mañana",
      "deadline": "4/10/25, 22:10",
      "url": "/la-liga/players/gabriel-suazo",
      "clause": 4410000,
      "clauseDeposited": null,
      "owner": null,
      "ownerUrl": "/user/kenzoxs-3728853",
      "clauseUnlockIn": "Disponible",
      "source": "mercado"
    },
    {
      "name": "Odysseas",
      "position": "PT",
      "team": "Sevilla",
      "price": 17200000,
      "listedPrice": 2910000,
      "timeRemaining": "mañana",
      "deadline": "4/10/25, 19:54",
      "url": "/la-liga/players/o-vlachodimos",
      "clause": null,
      "clauseDeposited": null,
      "owner": null,
      "ownerUrl": null,
      "clauseUnlockIn": "Disponible",
      "source": "mercado"
    },
    {
      "name": "Francés",
      "position": "DEF",
      "team": "Girona",
      "price": 1900000,
      "listedPrice": 650000,
      "timeRemaining": "mañana",
      "deadline": "4/10/25, 19:50",
      "url": "/la-liga/players/frances",
      "clause": 2439914,
      "clauseDeposited": 732457,
      "owner": null,
      "ownerUrl": "/user/emre-team-6720619",
      "clauseUnlockIn": "Disponible",
      "source": "mercado"
    },
    {
      "name": "Pépé",
      "position": "DEL",
      "team": "Villarreal",
      "price": 115300000,
      "listedPrice": 12000000,
      "timeRemaining": "mañana",
      "deadline": "4/10/25, 19:50",
      "url": "/la-liga/players/nicolas-pepe",
      "clause": 18000000,
      "clauseDeposited": null,
      "owner": null,
      "ownerUrl": "/user/emre-team-6720619",
      "clauseUnlockIn": "Disponible",
      "source": "mercado"
    },
    {
      "name": "Iván Romero",
      "position": "DEL",
      "team": "Levante",
      "price": 36300000,
      "listedPrice": 5700000,
      "timeRemaining": "mañana",
      "deadline": "4/10/25, 19:49",
      "url": "/la-liga/players/ivan-romero",
      "clause": 11850190,
      "clauseDeposited": 1650095,
      "owner": null,
      "ownerUrl": "/user/emre-team-6720619",
      "clauseUnlockIn": "Disponible",
      "source": "mercado"
    },
    {
      "name": "Asprilla",
      "position": "DEL",
      "team": "Girona",
      "price": 1890000,
      "listedPrice": 1870000,
      "timeRemaining": "mañana",
      "deadline": "4/10/25, 5:31",
      "url": "/la-liga/players/yaser-asprilla",
      "clause": null,
      "clauseDeposited": null,
      "owner": null,
      "ownerUrl": null,
      "clauseUnlockIn": "Disponible",
      "source": "mercado"
    },
    {
      "name": "Isi Palazón",
      "position": "DEL",
      "team": "Rayo Vallecano",
      "price": 4950000,
      "listedPrice": 4900000,
      "timeRemaining": "mañana",
      "deadline": "4/10/25, 5:30",
      "url": "/la-liga/players/isi-palazon",
      "clause": 7485000,
      "clauseDeposited": null,
      "owner": null,
      "ownerUrl": "/user/cd-guadalajara-8105116",
      "clauseUnlockIn": "Disponible",
      "source": "mercado"
    },
    {
      "name": "Iago Aspas",
      "position": "DEL",
      "team": "Celta",
      "price": 4770000,
      "listedPrice": 4680000,
      "timeRemaining": "mañana",
      "deadline": "4/10/25, 5:30",
      "url": "/la-liga/players/iago-aspas",
      "clause": 9900090,
      "clauseDeposited": null,
      "owner": null,
      "ownerUrl": "/user/cd-guadalajara-8105116",
      "clauseUnlockIn": "Disponible",
      "source": "mercado"
    },
    {
      "name": "Elgezabal",
      "position": "DEF",
      "team": "Levante",
      "price": 1480000,
      "listedPrice": 1460000,
      "timeRemaining": "mañana",
      "deadline": "4/10/25, 5:30",
      "url": "/la-liga/players/unai-elgezabal",
      "clause": 3225000,
      "clauseDeposited": null,
      "owner": null,
      "ownerUrl": "/user/cd-guadalajara-8105116",
      "clauseUnlockIn": "Disponible",
      "source": "mercado"
    },
    {
      "name": "Aramburu",
      "position": "DEF",
      "team": "Real Sociedad",
      "price": 2120000,
      "listedPrice": 2070000,
      "timeRemaining": "mañana",
      "deadline": "4/10/25, 5:29",
      "url": "/la-liga/players/jon-aramburu",
      "clause": 4335000,
      "clauseDeposited": null,
      "owner": null,
      "ownerUrl": "/user/cd-guadalajara-8105116",
      "clauseUnlockIn": "Disponible",
      "source": "mercado"
    },
    {
      "name": "Iñaki Peña",
      "position": "PT",
      "team": "Elche",
      "price": 4200000,
      "listedPrice": 2040000,
      "timeRemaining": "mañana",
      "deadline": "4/10/25, 5:04",
      "url": "/la-liga/players/inaki-pena",
      "clause": 4125000,
      "clauseDeposited": null,
      "owner": null,
      "ownerUrl": "/user/chacaritas-f-c-3712724",
      "clauseUnlockIn": "Disponible",
      "source": "mercado"
    },
    {
      "name": "Iván Villar",
      "position": "PT",
      "team": "Celta",
      "price": 360000,
      "listedPrice": 180000,
      "timeRemaining": "mañana",
      "deadline": "4/10/25, 5:04",
      "url": "/la-liga/players/ivan-villar",
      "clause": 270000,
      "clauseDeposited": null,
      "owner": null,
      "ownerUrl": "/user/chacaritas-f-c-3712724",
      "clauseUnlockIn": "Disponible",
      "source": "mercado"
    },
    {
      "name": "Ferran Torres",
      "position": "DEL",
      "team": "Barcelona",
      "price": 19080000,
      "listedPrice": 9610000,
      "timeRemaining": "mañana",
      "deadline": "4/10/25, 5:04",
      "url": "/la-liga/players/ferran-torres",
      "clause": 16415000,
      "clauseDeposited": 1000000,
      "owner": null,
      "ownerUrl": "/user/chacaritas-f-c-3712724",
      "clauseUnlockIn": "Disponible",
      "source": "mercado"
    },
    {
      "name": "Expósito",
      "position": "MED",
      "team": "Espanyol",
      "price": 9720000,
      "listedPrice": 4870000,
      "timeRemaining": "mañana",
      "deadline": "4/10/25, 5:04",
      "url": "/la-liga/players/edu-exposito-2",
      "clause": 8305000,
      "clauseDeposited": 500000,
      "owner": null,
      "ownerUrl": "/user/chacaritas-f-c-3712724",
      "clauseUnlockIn": "Disponible",
      "source": "mercado"
    },
    {
      "name": "Pathé Ciss",
      "position": "MED",
      "team": "Rayo Vallecano",
      "price": 11300000,
      "listedPrice": 5700000,
      "timeRemaining": "mañana",
      "deadline": "4/10/25, 5:04",
      "url": "/la-liga/players/pathe-ciss",
      "clause": 8550000,
      "clauseDeposited": null,
      "owner": null,
      "ownerUrl": "/user/chacaritas-f-c-3712724",
      "clauseUnlockIn": "Disponible",
      "source": "mercado"
    },
    {
      "name": "Abqar",
      "position": "DEF",
      "team": "Getafe",
      "price": 3160000,
      "listedPrice": 1630000,
      "timeRemaining": "mañana",
      "deadline": "4/10/25, 5:04",
      "url": "/la-liga/players/abdel-abqar",
      "clause": 2445000,
      "clauseDeposited": null,
      "owner": null,
      "ownerUrl": "/user/chacaritas-f-c-3712724",
      "clauseUnlockIn": "Disponible",
      "source": "mercado"
    },
    {
      "name": "Álvaro Carreras",
      "position": "DEF",
      "team": "Real Madrid",
      "price": 15360000,
      "listedPrice": 7710000,
      "timeRemaining": "mañana",
      "deadline": "4/10/25, 5:04",
      "url": "/la-liga/players/alvaro-fernandez-2",
      "clause": 11565000,
      "clauseDeposited": null,
      "owner": null,
      "ownerUrl": "/user/chacaritas-f-c-3712724",
      "clauseUnlockIn": "Disponible",
      "source": "mercado"
    },
    {
      "name": "Gerard Martín",
      "position": "DEF",
      "team": "Barcelona",
      "price": 6220000,
      "listedPrice": 3070000,
      "timeRemaining": "mañana",
      "deadline": "4/10/25, 5:04",
      "url": "/la-liga/players/gerard-martin",
      "clause": 4605000,
      "clauseDeposited": null,
      "owner": null,
      "ownerUrl": "/user/chacaritas-f-c-3712724",
      "clauseUnlockIn": "Disponible",
      "source": "mercado"
    },
    {
      "name": "Asencio",
      "position": "DEF",
      "team": "Real Madrid",
      "price": 2560000,
      "listedPrice": 1300000,
      "timeRemaining": "mañana",
      "deadline": "4/10/25, 5:04",
      "url": "/la-liga/players/raul-asencio",
      "clause": 1950000,
      "clauseDeposited": null,
      "owner": null,
      "ownerUrl": "/user/chacaritas-f-c-3712724",
      "clauseUnlockIn": "Disponible",
      "source": "mercado"
    },
    {
      "name": "Pétrot",
      "position": "DEF",
      "team": "Elche",
      "price": 1060000,
      "listedPrice": 530000,
      "timeRemaining": "mañana",
      "deadline": "4/10/25, 5:04",
      "url": "/la-liga/players/leo-petrot",
      "clause": 795000,
      "clauseDeposited": null,
      "owner": null,
      "ownerUrl": "/user/chacaritas-f-c-3712724",
      "clauseUnlockIn": "Disponible",
      "source": "mercado"
    },
    {
      "name": "Ali Houary",
      "position": "MED",
      "team": "Elche",
      "price": 300000,
      "listedPrice": 150000,
      "timeRemaining": "mañana",
      "deadline": "4/10/25, 5:04",
      "url": "/la-liga/players/ali-houary",
      "clause": 283500,
      "clauseDeposited": null,
      "owner": null,
      "ownerUrl": "/user/chacaritas-f-c-3712724",
      "clauseUnlockIn": "Disponible",
      "source": "mercado"
    },
    {
      "name": "Amrabat",
      "position": "MED",
      "team": "Betis",
      "price": 7900000,
      "listedPrice": 4020000,
      "timeRemaining": "mañana",
      "deadline": "4/10/25, 5:04",
      "url": "/la-liga/players/sofyan-amrabat",
      "clause": 6618000,
      "clauseDeposited": null,
      "owner": null,
      "ownerUrl": "/user/chacaritas-f-c-3712724",
      "clauseUnlockIn": "Disponible",
      "source": "mercado"
    },
    {
      "name": "Parejo",
      "position": "MED",
      "team": "Villarreal",
      "price": 4395000,
      "listedPrice": 2970000,
      "timeRemaining": "mañana",
      "deadline": "4/10/25, 5:04",
      "url": "/la-liga/players/parejo",
      "clause": 5070000,
      "clauseDeposited": null,
      "owner": null,
      "ownerUrl": "/user/tortelliniteam-3713353",
      "clauseUnlockIn": "Disponible",
      "source": "mercado"
    },
    {
      "name": "Militão",
      "position": "DEF",
      "team": "Real Madrid",
      "price": 10290000,
      "listedPrice": 6910000,
      "timeRemaining": "mañana",
      "deadline": "4/10/25, 5:04",
      "url": "/la-liga/players/eder-militao",
      "clause": 10365000,
      "clauseDeposited": null,
      "owner": null,
      "ownerUrl": "/user/tortelliniteam-3713353",
      "clauseUnlockIn": "Disponible",
      "source": "mercado"
    },
    {
      "name": "Raul García",
      "position": "DEL",
      "team": "Osasuna",
      "price": 1290000,
      "listedPrice": 860000,
      "timeRemaining": "mañana",
      "deadline": "4/10/25, 5:04",
      "url": "/la-liga/players/raul-garcia-2",
      "clause": 1455000,
      "clauseDeposited": null,
      "owner": null,
      "ownerUrl": "/user/tortelliniteam-3713353",
      "clauseUnlockIn": "Disponible",
      "source": "mercado"
    },
    {
      "name": "Febas",
      "position": "MED",
      "team": "Elche",
      "price": 4830000,
      "listedPrice": 3310000,
      "timeRemaining": "mañana",
      "deadline": "4/10/25, 5:04",
      "url": "/la-liga/players/aleix-febas",
      "clause": 4965000,
      "clauseDeposited": null,
      "owner": null,
      "ownerUrl": "/user/tortelliniteam-3713353",
      "clauseUnlockIn": "Disponible",
      "source": "mercado"
    },
    {
      "name": "Ilaix Moriba",
      "position": "MED",
      "team": "Celta",
      "price": 4815000,
      "listedPrice": 3180000,
      "timeRemaining": "mañana",
      "deadline": "4/10/25, 5:04",
      "url": "/la-liga/players/ilaix-moriba",
      "clause": 5310001,
      "clauseDeposited": null,
      "owner": null,
      "ownerUrl": "/user/tortelliniteam-3713353",
      "clauseUnlockIn": "Disponible",
      "source": "mercado"
    },
    {
      "name": "Danjuma",
      "position": "DEL",
      "team": "Valencia",
      "price": 6360000,
      "listedPrice": 4360000,
      "timeRemaining": "mañana",
      "deadline": "4/10/25, 5:04",
      "url": "/la-liga/players/arnaut-danjuma",
      "clause": 6540000,
      "clauseDeposited": null,
      "owner": null,
      "ownerUrl": "/user/tortelliniteam-3713353",
      "clauseUnlockIn": "Disponible",
      "source": "mercado"
    },
    {
      "name": "Sørloth",
      "position": "DEL",
      "team": "Atlético",
      "price": 6930000,
      "listedPrice": 4590000,
      "timeRemaining": "mañana",
      "deadline": "4/10/25, 5:04",
      "url": "/la-liga/players/a-sorloth",
      "clause": 7012500,
      "clauseDeposited": null,
      "owner": null,
      "ownerUrl": "/user/tortelliniteam-3713353",
      "clauseUnlockIn": "Disponible",
      "source": "mercado"
    },
    {
      "name": "Arda Güler",
      "position": "MED",
      "team": "Real Madrid",
      "price": 21555000,
      "listedPrice": 14450000,
      "timeRemaining": "mañana",
      "deadline": "4/10/25, 5:04",
      "url": "/la-liga/players/arda-guler",
      "clause": 23581396,
      "clauseDeposited": 953198,
      "owner": null,
      "ownerUrl": "/user/tortelliniteam-3713353",
      "clauseUnlockIn": "Disponible",
      "source": "mercado"
    },
    {
      "name": "Héctor Fort",
      "position": "DEF",
      "team": "Elche",
      "price": 1545000,
      "listedPrice": 1000000,
      "timeRemaining": "mañana",
      "deadline": "4/10/25, 5:04",
      "url": "/la-liga/players/hector-fort",
      "clause": 2880000,
      "clauseDeposited": null,
      "owner": null,
      "ownerUrl": "/user/tortelliniteam-3713353",
      "clauseUnlockIn": "Disponible",
      "source": "mercado"
    },
    {
      "name": "Javier Rueda",
      "position": "DEF",
      "team": "Celta",
      "price": 5895000,
      "listedPrice": 3910000,
      "timeRemaining": "mañana",
      "deadline": "4/10/25, 5:04",
      "url": "/la-liga/players/javier-rueda",
      "clause": 5865000,
      "clauseDeposited": null,
      "owner": null,
      "ownerUrl": "/user/tortelliniteam-3713353",
      "clauseUnlockIn": "Disponible",
      "source": "mercado"
    },
    {
      "name": "Ionut Radu",
      "position": "PT",
      "team": "Celta",
      "price": 4875000,
      "listedPrice": 3270000,
      "timeRemaining": "mañana",
      "deadline": "4/10/25, 5:04",
      "url": "/la-liga/players/ionut-radu",
      "clause": 4905000,
      "clauseDeposited": null,
      "owner": null,
      "ownerUrl": "/user/tortelliniteam-3713353",
      "clauseUnlockIn": "Disponible",
      "source": "mercado"
    },
    {
      "name": "Valentín Gómez",
      "position": "DEF",
      "team": "Betis",
      "price": 1845000,
      "listedPrice": 1310000,
      "timeRemaining": "mañana",
      "deadline": "4/10/25, 5:04",
      "url": "/la-liga/players/valentin-gomez",
      "clause": 2711000,
      "clauseDeposited": 373000,
      "owner": null,
      "ownerUrl": "/user/tortelliniteam-3713353",
      "clauseUnlockIn": "Disponible",
      "source": "mercado"
    },
    {
      "name": "Firpo",
      "position": "DEF",
      "team": "Betis",
      "price": 1580000,
      "listedPrice": 1540000,
      "timeRemaining": "mañana",
      "deadline": "4/10/25, 5:00",
      "url": "/la-liga/players/junior-firpo",
      "clause": null,
      "clauseDeposited": null,
      "owner": null,
      "ownerUrl": null,
      "clauseUnlockIn": "Disponible",
      "source": "mercado"
    },
    {
      "name": "Nyom",
      "position": "MED",
      "team": "Getafe",
      "price": 200000,
      "listedPrice": 200000,
      "timeRemaining": "mañana",
      "deadline": "4/10/25, 5:00",
      "url": "/la-liga/players/allan-nyom",
      "clause": null,
      "clauseDeposited": null,
      "owner": null,
      "ownerUrl": null,
      "clauseUnlockIn": "Disponible",
      "source": "mercado"
    },
    {
      "name": "Gavi",
      "position": "MED",
      "team": "Barcelona",
      "price": 2010000,
      "listedPrice": 1980000,
      "timeRemaining": "mañana",
      "deadline": "4/10/25, 5:00",
      "url": "/la-liga/players/gavi",
      "clause": null,
      "clauseDeposited": null,
      "owner": null,
      "ownerUrl": null,
      "clauseUnlockIn": "Disponible",
      "source": "mercado"
    },
    {
      "name": "Tenaglia",
      "position": "DEF",
      "team": "Alavés",
      "price": 3730000,
      "listedPrice": 3700000,
      "timeRemaining": "mañana",
      "deadline": "4/10/25, 5:00",
      "url": "/la-liga/players/nahuel-tenaglia",
      "clause": null,
      "clauseDeposited": null,
      "owner": null,
      "ownerUrl": null,
      "clauseUnlockIn": "Disponible",
      "source": "mercado"
    },
    {
      "name": "Jofre Carreras",
      "position": "MED",
      "team": "Espanyol",
      "price": 660000,
      "listedPrice": 660000,
      "timeRemaining": "mañana",
      "deadline": "4/10/25, 5:00",
      "url": "/la-liga/players/jofre-carreras",
      "clause": null,
      "clauseDeposited": null,
      "owner": null,
      "ownerUrl": null,
      "clauseUnlockIn": "Disponible",
      "source": "mercado"
    },
    {
      "name": "Kike Salas",
      "position": "DEF",
      "team": "Sevilla",
      "price": 2250000,
      "listedPrice": 2200000,
      "timeRemaining": "mañana",
      "deadline": "4/10/25, 5:00",
      "url": "/la-liga/players/kike-salas",
      "clause": null,
      "clauseDeposited": null,
      "owner": null,
      "ownerUrl": null,
      "clauseUnlockIn": "Disponible",
      "source": "mercado"
    },
    {
      "name": "Bryan Zaragoza",
      "position": "DEL",
      "team": "Celta",
      "price": 3710000,
      "listedPrice": 3660000,
      "timeRemaining": "mañana",
      "deadline": "4/10/25, 5:00",
      "url": "/la-liga/players/bryan-zaragoza",
      "clause": null,
      "clauseDeposited": null,
      "owner": null,
      "ownerUrl": null,
      "clauseUnlockIn": "Disponible",
      "source": "mercado"
    },
    {
      "name": "Antoniu Roca",
      "position": "DEL",
      "team": "Espanyol",
      "price": 220000,
      "listedPrice": 220000,
      "timeRemaining": "mañana",
      "deadline": "4/10/25, 5:00",
      "url": "/la-liga/players/antoniu-roca",
      "clause": null,
      "clauseDeposited": null,
      "owner": null,
      "ownerUrl": null,
      "clauseUnlockIn": "Disponible",
      "source": "mercado"
    },
    {
      "name": "Thiago Almada",
      "position": "MED",
      "team": "Atlético",
      "price": 3170000,
      "listedPrice": 3140000,
      "timeRemaining": "mañana",
      "deadline": "4/10/25, 5:00",
      "url": "/la-liga/players/thiago-almada",
      "clause": null,
      "clauseDeposited": null,
      "owner": null,
      "ownerUrl": null,
      "clauseUnlockIn": "Disponible",
      "source": "mercado"
    },
    {
      "name": "Iturbe",
      "position": "PT",
      "team": "Elche",
      "price": 180000,
      "listedPrice": 180000,
      "timeRemaining": "mañana",
      "deadline": "4/10/25, 5:00",
      "url": "/la-liga/players/iturbe",
      "clause": null,
      "clauseDeposited": null,
      "owner": null,
      "ownerUrl": null,
      "clauseUnlockIn": "Disponible",
      "source": "mercado"
    },
    {
      "name": "Goti",
      "position": "MED",
      "team": "Real Sociedad",
      "price": 150000,
      "listedPrice": 150000,
      "timeRemaining": "mañana",
      "deadline": "4/10/25, 5:00",
      "url": "/la-liga/players/mikel-goti",
      "clause": null,
      "clauseDeposited": null,
      "owner": null,
      "ownerUrl": null,
      "clauseUnlockIn": "Disponible",
      "source": "mercado"
    },
    {
      "name": "Neto",
      "position": "MED",
      "team": "Elche",
      "price": 13700000,
      "listedPrice": 1350000,
      "timeRemaining": "mañana",
      "deadline": "4/10/25, 4:37",
      "url": "/la-liga/players/martim-neto",
      "clause": 3363000,
      "clauseDeposited": 669000,
      "owner": null,
      "ownerUrl": "/user/emre-team-6720619",
      "clauseUnlockIn": "Disponible",
      "source": "mercado"
    },
    {
      "name": "Dani Olmo",
      "position": "MED",
      "team": "Barcelona",
      "price": 72600000,
      "listedPrice": 7370000,
      "timeRemaining": "mañana",
      "deadline": "4/10/25, 4:37",
      "url": "/la-liga/players/dani-olmo",
      "clause": 11055000,
      "clauseDeposited": null,
      "owner": null,
      "ownerUrl": "/user/emre-team-6720619",
      "clauseUnlockIn": "Disponible",
      "source": "mercado"
    },
    {
      "name": "Yusi Enríquez",
      "position": "DEF",
      "team": "Alavés",
      "price": 3700000,
      "listedPrice": 400000,
      "timeRemaining": "mañana",
      "deadline": "4/10/25, 4:37",
      "url": "/la-liga/players/yusi-enriquez",
      "clause": 660031,
      "clauseDeposited": null,
      "owner": null,
      "ownerUrl": "/user/emre-team-6720619",
      "clauseUnlockIn": "Disponible",
      "source": "mercado"
    },
    {
      "name": "Szczęsny",
      "position": "PT",
      "team": "Barcelona",
      "price": 10500000,
      "listedPrice": 2080000,
      "timeRemaining": "mañana",
      "deadline": "4/10/25, 4:36",
      "url": "/la-liga/players/szczesny",
      "clause": 3450336,
      "clauseDeposited": null,
      "owner": null,
      "ownerUrl": "/user/emre-team-6720619",
      "clauseUnlockIn": "Disponible",
      "source": "mercado"
    },
    {
      "name": "Víctor Muñoz",
      "position": "DEL",
      "team": "Osasuna",
      "price": 31500000,
      "listedPrice": 3420000,
      "timeRemaining": "mañana",
      "deadline": "4/10/25, 4:36",
      "url": "/la-liga/players/victor-munoz",
      "clause": 6060000,
      "clauseDeposited": 465000,
      "owner": null,
      "ownerUrl": "/user/emre-team-6720619",
      "clauseUnlockIn": "Disponible",
      "source": "mercado"
    },
    {
      "name": "Boyomo",
      "position": "DEF",
      "team": "Osasuna",
      "price": 23100000,
      "listedPrice": 5940000,
      "timeRemaining": "mañana",
      "deadline": "4/10/25, 4:35",
      "url": "/la-liga/players/enzo-boyomo",
      "clause": 8910000,
      "clauseDeposited": null,
      "owner": null,
      "ownerUrl": "/user/emre-team-6720619",
      "clauseUnlockIn": "Disponible",
      "source": "mercado"
    },
    {
      "name": "Sotelo",
      "position": "MED",
      "team": "Celta",
      "price": 16200000,
      "listedPrice": 5670000,
      "timeRemaining": "mañana",
      "deadline": "4/10/25, 4:35",
      "url": "/la-liga/players/hugo-sotelo",
      "clause": 8505000,
      "clauseDeposited": null,
      "owner": null,
      "ownerUrl": "/user/emre-team-6720619",
      "clauseUnlockIn": "Disponible",
      "source": "mercado"
    },
    {
      "name": "Julián Alvarez",
      "position": "DEL",
      "team": "Atlético",
      "price": 14110000,
      "listedPrice": 14110000,
      "timeRemaining": null,
      "deadline": null,
      "url": "/la-liga/players/j-alvarez",
      "clause": null,
      "clauseDeposited": null,
      "owner": null,
      "ownerUrl": null,
      "clauseUnlockIn": "Disponible",
      "source": "mercado"
    },
    {
      "name": "Koke",
      "position": "MED",
      "team": "Atlético",
      "price": 2930000,
      "listedPrice": 2930000,
      "timeRemaining": null,
      "deadline": null,
      "url": "/la-liga/players/koke",
      "clause": 6395000,
      "clauseDeposited": 1000000,
      "owner": null,
      "ownerUrl": "/user/forza-depor-3712719",
      "clauseUnlockIn": "Disponible",
      "source": "mercado"
    },
    {
      "name": "Etta Eyong",
      "position": "DEL",
      "team": "Levante",
      "price": 9340000,
      "listedPrice": 9340000,
      "timeRemaining": null,
      "deadline": null,
      "url": "/la-liga/players/etta-eyong",
      "clause": 17410000,
      "clauseDeposited": 1700000,
      "owner": null,
      "ownerUrl": "/user/kenzoxs-3728853",
      "clauseUnlockIn": "Disponible",
      "source": "mercado"
    },
    {
      "name": "Ez Abde",
      "position": "DEL",
      "team": "Betis",
      "price": 5000000,
      "listedPrice": 5000000,
      "timeRemaining": null,
      "deadline": null,
      "url": "/la-liga/players/abdessamad-ezzalzouli",
      "clause": 7723500,
      "clauseDeposited": null,
      "owner": null,
      "ownerUrl": "/user/forza-depor-3712719",
      "clauseUnlockIn": "Disponible",
      "source": "mercado"
    },
    {
      "name": "Sancet",
      "position": "MED",
      "team": "Athletic",
      "price": 7490000,
      "listedPrice": 7490000,
      "timeRemaining": null,
      "deadline": null,
      "url": "/la-liga/players/sancet",
      "clause": null,
      "clauseDeposited": null,
      "owner": null,
      "ownerUrl": null,
      "clauseUnlockIn": "Disponible",
      "source": "mercado"
    },
    {
      "name": "Cabrera",
      "position": "DEF",
      "team": "Espanyol",
      "price": 3350000,
      "listedPrice": 3350000,
      "timeRemaining": null,
      "deadline": null,
      "url": "/la-liga/players/leandro-cabrera",
      "clause": null,
      "clauseDeposited": null,
      "owner": null,
      "ownerUrl": null,
      "clauseUnlockIn": "Disponible",
      "source": "mercado"
    },
    {
      "name": "Raphinha",
      "position": "DEL",
      "team": "Barcelona",
      "price": 14720000,
      "listedPrice": 14720000,
      "timeRemaining": null,
      "deadline": null,
      "url": "/la-liga/players/raphinha",
      "clause": null,
      "clauseDeposited": null,
      "owner": null,
      "ownerUrl": null,
      "clauseUnlockIn": "Disponible",
      "source": "mercado"
    },
    {
      "name": "Carvajal",
      "position": "DEF",
      "team": "Real Madrid",
      "price": 4050000,
      "listedPrice": 4050000,
      "timeRemaining": null,
      "deadline": null,
      "url": "/la-liga/players/carvajal",
      "clause": null,
      "clauseDeposited": null,
      "owner": null,
      "ownerUrl": null,
      "clauseUnlockIn": "Disponible",
      "source": "mercado"
    }
  ]
}